{
    "train": {
        "index": [
            "Logistic Regression",
            "Decision Tree",
            "Random Forest",
            "Gradient Boosting",
            "XGBoost",
            "GaussianNB",
            "DNN",
            "DeepFM"
        ],
        "columns": [
            "Accuracy",
            "AUC",
            "TPR",
            "FPR",
            "TNR",
            "FNR"
        ],
        "data": [
            [
                0.998,
                0.568,
                0.0,
                0.0,
                1.0,
                1.0
            ],
            [
                0.998,
                0.555,
                0.018,
                0.0,
                1.0,
                0.982
            ],
            [
                0.998,
                0.594,
                0.018,
                0.0,
                1.0,
                0.982
            ],
            [
                0.998,
                0.6,
                0.0,
                0.0,
                1.0,
                1.0
            ],
            [
                0.998,
                0.694,
                0.018,
                0.0,
                1.0,
                0.982
            ],
            [
                0.994,
                0.571,
                0.088,
                0.004,
                0.996,
                0.912
            ],
            [
                0.998,
                0.613,
                0.0,
                0.0,
                1.0,
                1.0
            ],
            [
                0.998,
                0.595,
                0.0,
                0.0,
                1.0,
                1.0
            ]
        ]
    },
    "holdout": {
        "index": [
            "Logistic Regression",
            "Decision Tree",
            "Random Forest",
            "Gradient Boosting",
            "XGBoost",
            "GaussianNB",
            "DNN",
            "DeepFM"
        ],
        "columns": [
            "Accuracy",
            "AUC",
            "TPR",
            "FPR",
            "TNR",
            "FNR"
        ],
        "data": [
            [
                0.998,
                0.585,
                0.0,
                0.0,
                1.0,
                1.0
            ],
            [
                0.998,
                0.572,
                0.018,
                0.0,
                1.0,
                0.982
            ],
            [
                0.998,
                0.639,
                0.018,
                0.0,
                1.0,
                0.982
            ],
            [
                0.998,
                0.587,
                0.018,
                0.0,
                1.0,
                0.982
            ],
            [
                0.998,
                0.598,
                0.018,
                0.0,
                1.0,
                0.982
            ],
            [
                0.994,
                0.591,
                0.088,
                0.004,
                0.996,
                0.912
            ],
            [
                0.998,
                0.64,
                0.0,
                0.0,
                1.0,
                1.0
            ],
            [
                0.998,
                0.614,
                0.0,
                0.0,
                1.0,
                1.0
            ]
        ]
    },
    "synthetic_train": {
        "index": [
            "Logistic Regression",
            "Decision Tree",
            "Random Forest",
            "Gradient Boosting",
            "XGBoost",
            "GaussianNB",
            "DNN",
            "DeepFM"
        ],
        "columns": [
            "Accuracy",
            "AUC",
            "TPR",
            "FPR",
            "TNR",
            "FNR"
        ],
        "data": [
            [
                0.998,
                0.592,
                0.0,
                0.0,
                1.0,
                1.0
            ],
            [
                0.995,
                0.498,
                0.0,
                0.003,
                0.997,
                1.0
            ],
            [
                0.998,
                0.599,
                0.0,
                0.0,
                1.0,
                1.0
            ],
            [
                0.998,
                0.53,
                0.0,
                0.0,
                1.0,
                1.0
            ],
            [
                0.998,
                0.593,
                0.0,
                0.0,
                1.0,
                1.0
            ],
            [
                0.998,
                0.589,
                0.0,
                0.0,
                1.0,
                1.0
            ],
            [
                0.998,
                0.599,
                0.0,
                0.0,
                1.0,
                1.0
            ],
            [
                0.998,
                0.595,
                0.0,
                0.0,
                1.0,
                1.0
            ]
        ]
    }
}